{
  "product_id": "BDB015",
  "name_product": "DIANTHA KOKO",
  "new_product": false,
  "brand": {
    "name_brand": "nbrs"
  },
  "category3": "NBRS Rayya Series 2024",
  "description": "<p>Material Dobby Docia</p><p>- Dobby Docia merupakan kain woven fabric dengan anyaman Dobby, komposisi benang yang digunakan menggunakan serat alam dan benang sintetis, karakter kain ini bertekstur tapi tetap lembut dan halus. Kemudian bersifat absorber yang baik, jadi nyaman digunakan.</p><p><br></p><p>Detail Produk :</p><p>- Full Kancing</p><p>- Saku Depan</p><p>- Lengan Pendek</p><p><br></p><p>*Kesesuaian foto dan asli 90 - 100% dipengaruhi faktor cahaya pemotretan, editing dan resolusi cahaya hp masing-masing</p><p>*Kesesuaian standard sizepack dengan asli 1-2cm</p>",
  "thumbnails": [
    "https://nibras-web.sgp1.digitaloceanspaces.com/gon-old/DIANTHA_CASHMERE_BROWN_081.jpg",
    "https://nibras-web.sgp1.digitaloceanspaces.com/gudang-online-nibras-web/products/BDB015/240805113956-BDB015.jpeg",
    "https://nibras-web.sgp1.digitaloceanspaces.com/gudang-online-nibras-web/products/BDB015/240805011730-BDB015.jpeg",
    "https://nibras-web.sgp1.digitaloceanspaces.com/gudang-online-nibras-web/products/BDB015/240805011733-BDB015.jpeg",
    "https://nibras-web.sgp1.digitaloceanspaces.com/gudang-online-nibras-web/products/BDB015/240805011736-BDB015.jpeg",
    "https://nibras-web.sgp1.digitaloceanspaces.com/gudang-online-nibras-web/products/BDB015/240805011922-BDB015.jpeg",
    "https://nibras-web.sgp1.digitaloceanspaces.com/gudang-online-nibras-web/products/BDB015/240805011924-BDB015.jpeg",
    "https://nibras-web.sgp1.digitaloceanspaces.com/gudang-online-nibras-web/products/BDB015/240805011928-BDB015.jpeg",
    "https://nibras-web.sgp1.digitaloceanspaces.com/gudang-online-nibras-web/products/BDB015/240805011931-BDB015.jpeg",
    "https://nibras-web.sgp1.digitaloceanspaces.com/gudang-online-nibras-web/products/BDB015/240805012518-BDB015.jpeg",
    "https://nibras-web.sgp1.digitaloceanspaces.com/gudang-online-nibras-web/products/BDB015/240805012520-BDB015.jpeg",
    "https://nibras-web.sgp1.digitaloceanspaces.com/gudang-online-nibras-web/products/BDB015/240805012545-BDB015.jpeg",
    "https://nibras-web.sgp1.digitaloceanspaces.com/gudang-online-nibras-web/products/BDB015/240805012549-BDB015.jpeg"
  ],
  "thumbnails_main": "https://nibras-web.sgp1.digitaloceanspaces.com/gon-old/DIANTHA_CASHMERE_BROWN_081.jpg",
  "thumbnails_size_cart": "\"\"",
  "meta_description": "\"\"",
  "meta_keywords": [
    "diantha-koko",
    "diantha-koko"
  ],
  "meta_slug": "diantha-koko",
  "created_at": "2024-05-16T05:01:30.490Z",
  "variants": [
    {
      "code_model": "BDB015",
      "price_tags": 198000,
      "thumbnails": "https://nibras-web.sgp1.digitaloceanspaces.com/gon-old/DIANTHA_CASHMERE_BROWN_081.jpg",
      "sku": "BDB01502128",
      "variant1_size": "XS",
      "variant2_color": "PLUM",
      "stock": 14,
      "flag_stock_available": true,
      "package_weight": 233,
      "package_width": 0,
      "package_length": 0,
      "package_height": 0
    },
    {
      "code_model": "BDB015",
      "price_tags": 198000,
      "thumbnails": "https://nibras-web.sgp1.digitaloceanspaces.com/gon-old/DIANTHA_CASHMERE_BROWN_081.jpg",
      "sku": "BDB01502302",
      "variant1_size": "XS",
      "variant2_color": "BROWN",
      "stock": 0,
      "flag_stock_available": false,
      "package_weight": 233,
      "package_width": 0,
      "package_length": 0,
      "package_height": 0
    },
    {
      "code_model": "BDB015",
      "price_tags": 198000,
      "thumbnails": "https://nibras-web.sgp1.digitaloceanspaces.com/gon-old/DIANTHA_CASHMERE_BROWN_081.jpg",
      "sku": "BDB01502554",
      "variant1_size": "XS",
      "variant2_color": "OLIVE GREEN",
      "stock": 0,
      "flag_stock_available": false,
      "package_weight": 233,
      "package_width": 0,
      "package_length": 0,
      "package_height": 0
    },
    {
      "code_model": "BDB015",
      "price_tags": 198000,
      "thumbnails": "https://nibras-web.sgp1.digitaloceanspaces.com/gon-old/DIANTHA_CASHMERE_BROWN_081.jpg",
      "sku": "BDB01503128",
      "variant1_size": "S",
      "variant2_color": "PLUM",
      "stock": 0,
      "flag_stock_available": false,
      "package_weight": 233,
      "package_width": 0,
      "package_length": 0,
      "package_height": 0
    },
    {
      "code_model": "BDB015",
      "price_tags": 198000,
      "thumbnails": "https://nibras-web.sgp1.digitaloceanspaces.com/gon-old/DIANTHA_CASHMERE_BROWN_081.jpg",
      "sku": "BDB01503302",
      "variant1_size": "S",
      "variant2_color": "BROWN",
      "stock": 0,
      "flag_stock_available": false,
      "package_weight": 233,
      "package_width": 0,
      "package_length": 0,
      "package_height": 0
    },
    {
      "code_model": "BDB015",
      "price_tags": 198000,
      "thumbnails": "https://nibras-web.sgp1.digitaloceanspaces.com/gon-old/DIANTHA_CASHMERE_BROWN_081.jpg",
      "sku": "BDB01503554",
      "variant1_size": "S",
      "variant2_color": "OLIVE GREEN",
      "stock": 0,
      "flag_stock_available": false,
      "package_weight": 233,
      "package_width": 0,
      "package_length": 0,
      "package_height": 0
    },
    {
      "code_model": "BDB015",
      "price_tags": 198000,
      "thumbnails": "https://nibras-web.sgp1.digitaloceanspaces.com/gon-old/DIANTHA_CASHMERE_BROWN_081.jpg",
      "sku": "BDB01504128",
      "variant1_size": "M",
      "variant2_color": "PLUM",
      "stock": 0,
      "flag_stock_available": false,
      "package_weight": 233,
      "package_width": 0,
      "package_length": 0,
      "package_height": 0
    },
    {
      "code_model": "BDB015",
      "price_tags": 198000,
      "thumbnails": "https://nibras-web.sgp1.digitaloceanspaces.com/gon-old/DIANTHA_CASHMERE_BROWN_081.jpg",
      "sku": "BDB01504302",
      "variant1_size": "M",
      "variant2_color": "BROWN",
      "stock": 0,
      "flag_stock_available": false,
      "package_weight": 233,
      "package_width": 0,
      "package_length": 0,
      "package_height": 0
    },
    {
      "code_model": "BDB015",
      "price_tags": 198000,
      "thumbnails": "https://nibras-web.sgp1.digitaloceanspaces.com/gon-old/DIANTHA_CASHMERE_BROWN_081.jpg",
      "sku": "BDB01504554",
      "variant1_size": "M",
      "variant2_color": "OLIVE GREEN",
      "stock": 0,
      "flag_stock_available": false,
      "package_weight": 233,
      "package_width": 0,
      "package_length": 0,
      "package_height": 0
    },
    {
      "code_model": "BDB015",
      "price_tags": 198000,
      "thumbnails": "https://nibras-web.sgp1.digitaloceanspaces.com/gon-old/DIANTHA_CASHMERE_BROWN_081.jpg",
      "sku": "BDB01505128",
      "variant1_size": "L",
      "variant2_color": "PLUM",
      "stock": 0,
      "flag_stock_available": false,
      "package_weight": 264,
      "package_width": 0,
      "package_length": 0,
      "package_height": 0
    },
    {
      "code_model": "BDB015",
      "price_tags": 198000,
      "thumbnails": "https://nibras-web.sgp1.digitaloceanspaces.com/gon-old/DIANTHA_CASHMERE_BROWN_081.jpg",
      "sku": "BDB01505554",
      "variant1_size": "L",
      "variant2_color": "OLIVE GREEN",
      "stock": 0,
      "flag_stock_available": false,
      "package_weight": 264,
      "package_width": 0,
      "package_length": 0,
      "package_height": 0
    },
    {
      "code_model": "BDB015",
      "price_tags": 198000,
      "thumbnails": "https://nibras-web.sgp1.digitaloceanspaces.com/gon-old/DIANTHA_CASHMERE_BROWN_081.jpg",
      "sku": "BDB01506554",
      "variant1_size": "XL",
      "variant2_color": "OLIVE GREEN",
      "stock": 0,
      "flag_stock_available": false,
      "package_weight": 264,
      "package_width": 0,
      "package_length": 0,
      "package_height": 0
    },
    {
      "code_model": "BDB015",
      "price_tags": 210000,
      "thumbnails": "https://nibras-web.sgp1.digitaloceanspaces.com/gon-old/DIANTHA_CASHMERE_BROWN_081.jpg",
      "sku": "BDB01507128",
      "variant1_size": "XXL",
      "variant2_color": "PLUM",
      "stock": 0,
      "flag_stock_available": false,
      "package_weight": 276,
      "package_width": 0,
      "package_length": 0,
      "package_height": 0
    },
    {
      "code_model": "BDB015",
      "price_tags": 210000,
      "thumbnails": "https://nibras-web.sgp1.digitaloceanspaces.com/gon-old/DIANTHA_CASHMERE_BROWN_081.jpg",
      "sku": "BDB01507302",
      "variant1_size": "XXL",
      "variant2_color": "BROWN",
      "stock": 0,
      "flag_stock_available": false,
      "package_weight": 276,
      "package_width": 0,
      "package_length": 0,
      "package_height": 0
    },
    {
      "code_model": "BDB015",
      "price_tags": 220000,
      "thumbnails": "https://nibras-web.sgp1.digitaloceanspaces.com/gon-old/DIANTHA_CASHMERE_BROWN_081.jpg",
      "sku": "BDB01566128",
      "variant1_size": "3XL",
      "variant2_color": "PLUM",
      "stock": 0,
      "flag_stock_available": false,
      "package_weight": 284,
      "package_width": 0,
      "package_length": 0,
      "package_height": 0
    },
    {
      "code_model": "BDB015",
      "price_tags": 220000,
      "thumbnails": "https://nibras-web.sgp1.digitaloceanspaces.com/gon-old/DIANTHA_CASHMERE_BROWN_081.jpg",
      "sku": "BDB01566554",
      "variant1_size": "3XL",
      "variant2_color": "OLIVE GREEN",
      "stock": 0,
      "flag_stock_available": false,
      "package_weight": 284,
      "package_width": 0,
      "package_length": 0,
      "package_height": 0
    },
    {
      "code_model": "BDB015",
      "price_tags": 230000,
      "thumbnails": "https://nibras-web.sgp1.digitaloceanspaces.com/gon-old/DIANTHA_CASHMERE_BROWN_081.jpg",
      "sku": "BDB01567128",
      "variant1_size": "4XL",
      "variant2_color": "PLUM",
      "stock": 0,
      "flag_stock_available": false,
      "package_weight": 294,
      "package_width": 0,
      "package_length": 0,
      "package_height": 0
    },
    {
      "code_model": "BDB015",
      "price_tags": 230000,
      "thumbnails": "https://nibras-web.sgp1.digitaloceanspaces.com/gon-old/DIANTHA_CASHMERE_BROWN_081.jpg",
      "sku": "BDB01567302",
      "variant1_size": "4XL",
      "variant2_color": "BROWN",
      "stock": 0,
      "flag_stock_available": false,
      "package_weight": 294,
      "package_width": 0,
      "package_length": 0,
      "package_height": 0
    },
    {
      "code_model": "BDB015",
      "price_tags": 230000,
      "thumbnails": "https://nibras-web.sgp1.digitaloceanspaces.com/gon-old/DIANTHA_CASHMERE_BROWN_081.jpg",
      "sku": "BDB01567554",
      "variant1_size": "4XL",
      "variant2_color": "OLIVE GREEN",
      "stock": 0,
      "flag_stock_available": false,
      "package_weight": 294,
      "package_width": 0,
      "package_length": 0,
      "package_height": 0
    },
    {
      "code_model": "BDB015",
      "price_tags": 240000,
      "thumbnails": "https://nibras-web.sgp1.digitaloceanspaces.com/gon-old/DIANTHA_CASHMERE_BROWN_081.jpg",
      "sku": "BDB01568128",
      "variant1_size": "5XL",
      "variant2_color": "PLUM",
      "stock": 0,
      "flag_stock_available": false,
      "package_weight": 306,
      "package_width": 0,
      "package_length": 0,
      "package_height": 0
    },
    {
      "code_model": "BDB015",
      "price_tags": 240000,
      "thumbnails": "https://nibras-web.sgp1.digitaloceanspaces.com/gon-old/DIANTHA_CASHMERE_BROWN_081.jpg",
      "sku": "BDB01568554",
      "variant1_size": "5XL",
      "variant2_color": "OLIVE GREEN",
      "stock": 0,
      "flag_stock_available": false,
      "package_weight": 306,
      "package_width": 0,
      "package_length": 0,
      "package_height": 0
    }
  ],
  "diskon_product": 30
}