{
  "product_id": "BBC025",
  "name_product": "IMANA PANTS",
  "new_product": false,
  "brand": {
    "name_brand": "alnita"
  },
  "category3": "Alnita Sport",
  "description": "<p>Material Scuba, termasuk dalam bahan sintetis, karena dihasilkan dari pencampuran bahan polyester dan spandeks. Kandungan polyester dan spandeks dalam scuba menjadikan bahan ini elastis.</p><p><br></p><p>Detail Produk :</p><p>- Pinggang Full Karet</p><p>- Saku Sisi</p><p><br></p><p>*Kesesuaian foto dan asli 90 - 100% dipengaruhi faktor cahaya pemotretan, editing dan resolusi cahaya hp masing-masing</p><p>*Kesesuaian standard sizepack dengan asli 1-2cm</p>",
  "thumbnails": [
    "https://nibras-web.sgp1.digitaloceanspaces.com/gudang-online-nibras-web/products/BBC025/240820115038-BBC025.jpeg",
    "https://nibras-web.sgp1.digitaloceanspaces.com/gudang-online-nibras-web/products/BBC025/240820115106-BBC025.jpeg",
    "https://nibras-web.sgp1.digitaloceanspaces.com/gudang-online-nibras-web/products/BBC025/240820115048-BBC025.jpeg",
    "https://nibras-web.sgp1.digitaloceanspaces.com/gudang-online-nibras-web/products/BBC025/240820115100-BBC025.jpeg",
    "https://nibras-web.sgp1.digitaloceanspaces.com/gudang-online-nibras-web/products/BBC025/240820115254-BBC025.jpeg"
  ],
  "thumbnails_main": "https://nibras-web.sgp1.digitaloceanspaces.com/gudang-online-nibras-web/products/BBC025/thumbnail-240820115027-BBC025.jpeg",
  "thumbnails_size_cart": "\"\"",
  "meta_description": "\"\"",
  "meta_keywords": [
    "imana-pants",
    "imana-pants"
  ],
  "meta_slug": "imana-pants",
  "created_at": "2024-05-16T05:01:30.490Z",
  "variants": [
    {
      "code_model": "BBC025",
      "price_tags": 165000,
      "thumbnails": "https://nibras-web.sgp1.digitaloceanspaces.com/gon-old/WhatsApp_Image_2022-08-24_at_08.04_.46_(1)_.jpeg",
      "sku": "BBC02503114",
      "variant1_size": "S",
      "variant2_color": "WHITE",
      "stock": 0,
      "flag_stock_available": false,
      "package_weight": 372,
      "package_width": 0,
      "package_length": 0,
      "package_height": 0
    },
    {
      "code_model": "BBC025",
      "price_tags": 165000,
      "thumbnails": "https://nibras-web.sgp1.digitaloceanspaces.com/gon-old/WhatsApp_Image_2022-08-24_at_08.04_.46_(1)_.jpeg",
      "sku": "BBC02503135",
      "variant1_size": "S",
      "variant2_color": "DARK GREY",
      "stock": 2,
      "flag_stock_available": true,
      "package_weight": 372,
      "package_width": 0,
      "package_length": 0,
      "package_height": 0
    },
    {
      "code_model": "BBC025",
      "price_tags": 165000,
      "thumbnails": "https://nibras-web.sgp1.digitaloceanspaces.com/gon-old/WhatsApp_Image_2022-08-24_at_08.04_.46_(1)_.jpeg",
      "sku": "BBC02503202",
      "variant1_size": "S",
      "variant2_color": "BLACK",
      "stock": 0,
      "flag_stock_available": false,
      "package_weight": 372,
      "package_width": 0,
      "package_length": 0,
      "package_height": 0
    },
    {
      "code_model": "BBC025",
      "price_tags": 165000,
      "thumbnails": "https://nibras-web.sgp1.digitaloceanspaces.com/gon-old/WhatsApp_Image_2022-08-24_at_08.04_.46_(1)_.jpeg",
      "sku": "BBC02503575",
      "variant1_size": "S",
      "variant2_color": "ESTATE BLUE",
      "stock": 1,
      "flag_stock_available": true,
      "package_weight": 372,
      "package_width": 0,
      "package_length": 0,
      "package_height": 0
    },
    {
      "code_model": "BBC025",
      "price_tags": 165000,
      "thumbnails": "https://nibras-web.sgp1.digitaloceanspaces.com/gon-old/WhatsApp_Image_2022-08-24_at_08.04_.46_(1)_.jpeg",
      "sku": "BBC02504114",
      "variant1_size": "M",
      "variant2_color": "WHITE",
      "stock": 0,
      "flag_stock_available": false,
      "package_weight": 372,
      "package_width": 0,
      "package_length": 0,
      "package_height": 0
    },
    {
      "code_model": "BBC025",
      "price_tags": 165000,
      "thumbnails": "https://nibras-web.sgp1.digitaloceanspaces.com/gon-old/WhatsApp_Image_2022-08-24_at_08.04_.46_(1)_.jpeg",
      "sku": "BBC02504135",
      "variant1_size": "M",
      "variant2_color": "DARK GREY",
      "stock": 4,
      "flag_stock_available": true,
      "package_weight": 372,
      "package_width": 0,
      "package_length": 0,
      "package_height": 0
    },
    {
      "code_model": "BBC025",
      "price_tags": 165000,
      "thumbnails": "https://nibras-web.sgp1.digitaloceanspaces.com/gon-old/WhatsApp_Image_2022-08-24_at_08.04_.46_(1)_.jpeg",
      "sku": "BBC02504202",
      "variant1_size": "M",
      "variant2_color": "BLACK",
      "stock": 0,
      "flag_stock_available": false,
      "package_weight": 372,
      "package_width": 0,
      "package_length": 0,
      "package_height": 0
    },
    {
      "code_model": "BBC025",
      "price_tags": 165000,
      "thumbnails": "https://nibras-web.sgp1.digitaloceanspaces.com/gon-old/WhatsApp_Image_2022-08-24_at_08.04_.46_(1)_.jpeg",
      "sku": "BBC02504575",
      "variant1_size": "M",
      "variant2_color": "ESTATE BLUE",
      "stock": 0,
      "flag_stock_available": false,
      "package_weight": 372,
      "package_width": 0,
      "package_length": 0,
      "package_height": 0
    },
    {
      "code_model": "BBC025",
      "price_tags": 165000,
      "thumbnails": "https://nibras-web.sgp1.digitaloceanspaces.com/gon-old/WhatsApp_Image_2022-08-24_at_08.04_.46_(1)_.jpeg",
      "sku": "BBC02505114",
      "variant1_size": "L",
      "variant2_color": "WHITE",
      "stock": 0,
      "flag_stock_available": false,
      "package_weight": 436,
      "package_width": 0,
      "package_length": 0,
      "package_height": 0
    },
    {
      "code_model": "BBC025",
      "price_tags": 165000,
      "thumbnails": "https://nibras-web.sgp1.digitaloceanspaces.com/gon-old/WhatsApp_Image_2022-08-24_at_08.04_.46_(1)_.jpeg",
      "sku": "BBC02505135",
      "variant1_size": "L",
      "variant2_color": "DARK GREY",
      "stock": 0,
      "flag_stock_available": false,
      "package_weight": 436,
      "package_width": 0,
      "package_length": 0,
      "package_height": 0
    },
    {
      "code_model": "BBC025",
      "price_tags": 165000,
      "thumbnails": "https://nibras-web.sgp1.digitaloceanspaces.com/gon-old/WhatsApp_Image_2022-08-24_at_08.04_.46_(1)_.jpeg",
      "sku": "BBC02505202",
      "variant1_size": "L",
      "variant2_color": "BLACK",
      "stock": 0,
      "flag_stock_available": false,
      "package_weight": 436,
      "package_width": 0,
      "package_length": 0,
      "package_height": 0
    },
    {
      "code_model": "BBC025",
      "price_tags": 165000,
      "thumbnails": "https://nibras-web.sgp1.digitaloceanspaces.com/gon-old/WhatsApp_Image_2022-08-24_at_08.04_.46_(1)_.jpeg",
      "sku": "BBC02505575",
      "variant1_size": "L",
      "variant2_color": "ESTATE BLUE",
      "stock": 0,
      "flag_stock_available": false,
      "package_weight": 436,
      "package_width": 0,
      "package_length": 0,
      "package_height": 0
    },
    {
      "code_model": "BBC025",
      "price_tags": 165000,
      "thumbnails": "https://nibras-web.sgp1.digitaloceanspaces.com/gon-old/WhatsApp_Image_2022-08-24_at_08.04_.46_(1)_.jpeg",
      "sku": "BBC02506135",
      "variant1_size": "XL",
      "variant2_color": "DARK GREY",
      "stock": 0,
      "flag_stock_available": false,
      "package_weight": 436,
      "package_width": 0,
      "package_length": 0,
      "package_height": 0
    },
    {
      "code_model": "BBC025",
      "price_tags": 165000,
      "thumbnails": "https://nibras-web.sgp1.digitaloceanspaces.com/gon-old/WhatsApp_Image_2022-08-24_at_08.04_.46_(1)_.jpeg",
      "sku": "BBC02506575",
      "variant1_size": "XL",
      "variant2_color": "ESTATE BLUE",
      "stock": 0,
      "flag_stock_available": false,
      "package_weight": 436,
      "package_width": 0,
      "package_length": 0,
      "package_height": 0
    },
    {
      "code_model": "BBC025",
      "price_tags": 175000,
      "thumbnails": "https://nibras-web.sgp1.digitaloceanspaces.com/gon-old/WhatsApp_Image_2022-08-24_at_08.04_.46_(1)_.jpeg",
      "sku": "BBC02507114",
      "variant1_size": "XXL",
      "variant2_color": "WHITE",
      "stock": 0,
      "flag_stock_available": false,
      "package_weight": 450,
      "package_width": 0,
      "package_length": 0,
      "package_height": 0
    },
    {
      "code_model": "BBC025",
      "price_tags": 175000,
      "thumbnails": "https://nibras-web.sgp1.digitaloceanspaces.com/gon-old/WhatsApp_Image_2022-08-24_at_08.04_.46_(1)_.jpeg",
      "sku": "BBC02507135",
      "variant1_size": "XXL",
      "variant2_color": "DARK GREY",
      "stock": 0,
      "flag_stock_available": false,
      "package_weight": 450,
      "package_width": 0,
      "package_length": 0,
      "package_height": 0
    },
    {
      "code_model": "BBC025",
      "price_tags": 175000,
      "thumbnails": "https://nibras-web.sgp1.digitaloceanspaces.com/gon-old/WhatsApp_Image_2022-08-24_at_08.04_.46_(1)_.jpeg",
      "sku": "BBC02507575",
      "variant1_size": "XXL",
      "variant2_color": "ESTATE BLUE",
      "stock": 0,
      "flag_stock_available": false,
      "package_weight": 450,
      "package_width": 0,
      "package_length": 0,
      "package_height": 0
    }
  ],
  "diskon_product": 30
}